jsccf/__init__.py
jsccf/__main__.py
jsccf/jsccf.py
jsccf/jslexer.py
jsccf/jsrename.py
jsccf-0.8.0.dist-info/entry_points.txt
jsccf-0.8.0.dist-info/LICENSE
jsccf-0.8.0.dist-info/WHEEL
jsccf-0.8.0.dist-info/METADATA
jsccf-0.8.0.dist-info/RECORD
