Metadata-Version: 2.1
Name: jsccf
Version: 0.8.0
Summary: Renaming and documenting tool for JavaScript
Author: Sergei
Author-email: isara.isara8@gmail.com
Requires-Python: >=3.6,<4.0
Classifier: Programming Language :: Python :: 3
Classifier: Programming Language :: Python :: 3.6
Classifier: Programming Language :: Python :: 3.7
Classifier: Programming Language :: Python :: 3.8
Classifier: Programming Language :: Python :: 3.9
